llm_eval_toolkit/__init__.py
llm_eval_toolkit/cache_utils.py
llm_eval_toolkit/cli.py
llm_eval_toolkit/evaluator.py
llm_eval_toolkit-1.0.4.dist-info/licenses/LICENSE
llm_eval_toolkit-1.0.4.dist-info/METADATA
llm_eval_toolkit-1.0.4.dist-info/WHEEL
llm_eval_toolkit-1.0.4.dist-info/top_level.txt
llm_eval_toolkit-1.0.4.dist-info/RECORD
