Metadata-Version: 2.4
Name: llm-eval-toolkit
Version: 1.0.4
Summary: A comprehensive evaluation toolkit for Large Language Models
Home-page: https://github.com/AnSwati/llm_eval_toolkit
Author: Swati Tyagi
Author-email: Swati Tyagi <swatyagi@udel.edu>
License: MIT
Project-URL: Homepage, https://github.com/AnSwati/llm_eval_toolkit
Project-URL: Repository, https://github.com/AnSwati/llm_eval_toolkit
Project-URL: Issues, https://github.com/AnSwati/llm_eval_toolkit
Classifier: Development Status :: 3 - Alpha
Classifier: Intended Audience :: Developers
Classifier: License :: OSI Approved :: MIT License
Classifier: Programming Language :: Python :: 3
Classifier: Programming Language :: Python :: 3.8
Classifier: Programming Language :: Python :: 3.9
Classifier: Programming Language :: Python :: 3.10
Classifier: Programming Language :: Python :: 3.11
Classifier: Programming Language :: Python :: 3.12
Classifier: Programming Language :: Python :: 3.13
Requires-Python: >=3.8
License-File: LICENSE
Requires-Dist: transformers>=4.21.0
Requires-Dist: torch>=1.12.0
Requires-Dist: nltk>=3.8
Requires-Dist: sentence-transformers>=2.2.0
Requires-Dist: numpy>=1.21.0
Requires-Dist: pandas>=1.3.0
Requires-Dist: scikit-learn>=1.0.0
Requires-Dist: datasets>=2.0.0
Requires-Dist: evaluate>=0.4.0
Requires-Dist: rouge-score>=0.1.2
Requires-Dist: bert-score>=0.3.11
Requires-Dist: mauve-text>=0.3.0
Requires-Dist: textstat>=0.7.0
Requires-Dist: spacy>=3.4.0
Requires-Dist: sacrebleu>=2.0.0
Provides-Extra: dev
Requires-Dist: pytest>=6.0; extra == "dev"
Requires-Dist: pytest-cov>=2.0; extra == "dev"
Requires-Dist: black>=22.0; extra == "dev"
Requires-Dist: flake8>=4.0; extra == "dev"
Dynamic: author
Dynamic: home-page
Dynamic: license-file
Dynamic: requires-python
